seatools/ioc/starters/redis/__init__.py
seatools/ioc/starters/redis/redis.py
seatools_starter_redis-1.0.3.dist-info/LICENSE
seatools_starter_redis-1.0.3.dist-info/METADATA
seatools_starter_redis-1.0.3.dist-info/WHEEL
seatools_starter_redis-1.0.3.dist-info/top_level.txt
seatools_starter_redis-1.0.3.dist-info/RECORD
