Metadata-Version: 2.1
Name: seatools-starter-redis
Version: 1.0.3
Summary: seatools ioc redis 启动器
Home-page: https://gitee.com/seatools-py/seatools-starter-redis
Author: dragons96
Author-email: 521274311@qq.com
License: MIT license
Keywords: seatools,ioc,starter,redis
Classifier: Development Status :: 2 - Pre-Alpha
Classifier: Intended Audience :: Developers
Classifier: License :: OSI Approved :: MIT License
Classifier: Natural Language :: English
Classifier: Programming Language :: Python :: 3.9
Requires-Python: >=3.9
License-File: LICENSE
Requires-Dist: seatools >=1.0.22
Requires-Dist: loguru
Requires-Dist: redis
